setup.py
pymj/__init__.py
pymj.egg-info/PKG-INFO
pymj.egg-info/SOURCES.txt
pymj.egg-info/dependency_links.txt
pymj.egg-info/requires.txt
pymj.egg-info/top_level.txt