Metadata-Version: 1.0
Name: pymj
Version: 2.1
Summary: DEPRECATED -- use mujoco-py instead: https://github.com/openai/mujoco-py
Home-page: https://github.com/openai/mujoco-py
Author: OpenAI Robotics Team
Author-email: robotics@openai.com
License: UNKNOWN
Platform: UNKNOWN
